{
  "pageType": "guide",
  "slug": "first-home-buyer-suburbs-darwin",
  "seoTitle": "Best first-home-buyer-suburbs in Darwin — Climate Risk Guide | ClimateNest",
  "seoDescription": "Find the safest first-home-buyer-suburbs in Darwin based on climate risk scores. Compare flood, bushfire, heat, and storm risk across Darwin suburbs.",
  "ogTitle": "Best first-home-buyer-suburbs in Darwin",
  "ogDescription": "Climate-safe suburbs in Darwin ranked by risk score.",
  "heading": "Best first-home-buyer-suburbs in Darwin for Climate Safety",
  "intro": "Looking for first-home-buyer-suburbs in Darwin? Climate risk is an increasingly important factor in property decisions. Below we rank Darwin suburbs by overall climate risk score, from safest to highest risk, using data from BOM, CSIRO, and state hazard authorities.",
  "suburbs": [
    "alyangula",
    "angurugu",
    "baines",
    "canteen-creek",
    "cox-peninsula",
    "daguragu",
    "elsey",
    "coomalie-creek",
    "eaton",
    "bakewell"
  ],
  "paragraphs": [
    "Climate risk affects property values, insurance costs, and long-term liveability. Darwin's suburbs vary significantly in their exposure to flood, bushfire, extreme heat, and storm hazards. This guide ranks the top 10 safest suburbs in Darwin for first-home-buyer-suburbs.",
    "Remember that suburb-level scores are indicative. Every property within a suburb has a unique risk profile depending on its exact location, elevation, proximity to vegetation or waterways, and building characteristics. Always get an address-level report for the specific property you're considering."
  ],
  "rankedSuburbs": [
    {
      "name": "Alyangula",
      "score": 24,
      "slug": "alyangula",
      "state": "nt"
    },
    {
      "name": "Angurugu",
      "score": 24,
      "slug": "angurugu",
      "state": "nt"
    },
    {
      "name": "Baines",
      "score": 24,
      "slug": "baines",
      "state": "nt"
    },
    {
      "name": "Canteen Creek",
      "score": 25,
      "slug": "canteen-creek",
      "state": "nt"
    },
    {
      "name": "Cox Peninsula",
      "score": 25,
      "slug": "cox-peninsula",
      "state": "nt"
    },
    {
      "name": "Daguragu",
      "score": 25,
      "slug": "daguragu",
      "state": "nt"
    },
    {
      "name": "Elsey",
      "score": 25,
      "slug": "elsey",
      "state": "nt"
    },
    {
      "name": "Coomalie Creek",
      "score": 26,
      "slug": "coomalie-creek",
      "state": "nt"
    },
    {
      "name": "Eaton",
      "score": 26,
      "slug": "eaton",
      "state": "nt"
    },
    {
      "name": "Bakewell",
      "score": 27,
      "slug": "bakewell",
      "state": "nt"
    }
  ],
  "faq": [
    {
      "question": "What are the safest suburbs in Darwin for first-home-buyer-suburbs?",
      "answer": "Based on our analysis, Alyangula has the lowest overall climate risk score (24/100) in Darwin, followed by Angurugu and Baines. These scores combine flood, bushfire, heat, storm, and other hazard assessments."
    },
    {
      "question": "How does climate risk affect property in Darwin?",
      "answer": "Climate risk can impact insurance premiums, property resale value, and long-term ownership costs in Darwin. Properties in higher-risk areas may face increasing insurance costs and potential value depreciation. A full climate risk report provides detailed projections."
    }
  ],
  "internalLinks": [
    {
      "label": "Alyangula Climate Risk",
      "url": "/suburbs/nt/alyangula/climate-safety"
    },
    {
      "label": "Angurugu Climate Risk",
      "url": "/suburbs/nt/angurugu/climate-safety"
    },
    {
      "label": "Baines Climate Risk",
      "url": "/suburbs/nt/baines/climate-safety"
    },
    {
      "label": "Canteen Creek Climate Risk",
      "url": "/suburbs/nt/canteen-creek/climate-safety"
    },
    {
      "label": "Cox Peninsula Climate Risk",
      "url": "/suburbs/nt/cox-peninsula/climate-safety"
    },
    {
      "label": "Daguragu Climate Risk",
      "url": "/suburbs/nt/daguragu/climate-safety"
    },
    {
      "label": "Elsey Climate Risk",
      "url": "/suburbs/nt/elsey/climate-safety"
    },
    {
      "label": "Coomalie Creek Climate Risk",
      "url": "/suburbs/nt/coomalie-creek/climate-safety"
    },
    {
      "label": "Eaton Climate Risk",
      "url": "/suburbs/nt/eaton/climate-safety"
    },
    {
      "label": "Bakewell Climate Risk",
      "url": "/suburbs/nt/bakewell/climate-safety"
    }
  ]
}