{
  "pageType": "comparison",
  "slug": "glen-echo-vs-glen-esk",
  "seoTitle": "Glen Echo vs Glen Esk — Climate Risk Comparison | ClimateNest",
  "seoDescription": "Compare climate risk scores between Glen Echo and Glen Esk. See which suburb is safer from flood, bushfire, heat, and storm hazards.",
  "ogTitle": "Glen Echo vs Glen Esk: Climate Safety",
  "ogDescription": "Data-driven comparison of climate risk in Glen Echo and Glen Esk.",
  "heading": "Glen Echo vs Glen Esk — Which is Safer?",
  "intro": "Compare climate risk between Glen Echo, Queensland and Glen Esk, Queensland. Our analysis uses data from BOM, CSIRO, and state hazard authorities to score each suburb across 6 climate hazards.",
  "suburbs": [
    "glen-echo",
    "glen-esk"
  ],
  "hazards": [
    {
      "name": "Flood",
      "scoreA": 38,
      "scoreB": 51
    },
    {
      "name": "Bushfire",
      "scoreA": 33,
      "scoreB": 47
    },
    {
      "name": "Heat",
      "scoreA": 34,
      "scoreB": 45
    },
    {
      "name": "Storm",
      "scoreA": 30,
      "scoreB": 25
    },
    {
      "name": "Coastal",
      "scoreA": 52,
      "scoreB": 32
    },
    {
      "name": "Cyclone",
      "scoreA": 11,
      "scoreB": 22
    }
  ],
  "verdict": "Glen Echo has a lower overall climate risk score (33/100) compared to Glen Esk (37/100). We recommend getting an address-level report for properties in both suburbs before making a purchase decision.",
  "verdictClass": "positive",
  "faq": [
    {
      "question": "Is Glen Echo or Glen Esk safer from flooding?",
      "answer": "Glen Echo has a flood risk score of 38/100, while Glen Esk scores 51/100. A lower score indicates lower flood risk. Get an address-level flood risk report for a specific property."
    },
    {
      "question": "Which suburb has lower bushfire risk?",
      "answer": "Glen Echo scores 33/100 for bushfire risk. Glen Esk scores 47/100. Fire risk depends on proximity to vegetation and local fire history."
    },
    {
      "question": "Should I buy in Glen Echo or Glen Esk?",
      "answer": "Both suburbs have climate considerations. Glen Echo has a lower overall climate risk score. We recommend getting a full ClimateNest report for any specific property you're considering, which includes 8 hazard scores, insurance projections, and actionable recommendations."
    }
  ],
  "internalLinks": [
    {
      "label": "Glen Echo Flood Risk",
      "url": "/suburbs/qld/glen-echo/flood-risk"
    },
    {
      "label": "Glen Esk Flood Risk",
      "url": "/suburbs/qld/glen-esk/flood-risk"
    },
    {
      "label": "Glen Echo Should I Buy?",
      "url": "/suburbs/qld/glen-echo/should-i-buy"
    },
    {
      "label": "Glen Esk Should I Buy?",
      "url": "/suburbs/qld/glen-esk/should-i-buy"
    }
  ]
}