{
  "pageType": "comparison",
  "slug": "leumeah-vs-leura",
  "seoTitle": "Leumeah vs Leura — Climate Risk Comparison | ClimateNest",
  "seoDescription": "Compare climate risk scores between Leumeah and Leura. See which suburb is safer from flood, bushfire, heat, and storm hazards.",
  "ogTitle": "Leumeah vs Leura: Climate Safety",
  "ogDescription": "Data-driven comparison of climate risk in Leumeah and Leura.",
  "heading": "Leumeah vs Leura — Which is Safer?",
  "intro": "Compare climate risk between Leumeah, New South Wales and Leura, New South Wales. Our analysis uses data from BOM, CSIRO, and state hazard authorities to score each suburb across 6 climate hazards.",
  "suburbs": [
    "leumeah",
    "leura"
  ],
  "hazards": [
    {
      "name": "Flood",
      "scoreA": 27,
      "scoreB": 27
    },
    {
      "name": "Bushfire",
      "scoreA": 37,
      "scoreB": 49
    },
    {
      "name": "Heat",
      "scoreA": 66,
      "scoreB": 54
    },
    {
      "name": "Storm",
      "scoreA": 42,
      "scoreB": 37
    },
    {
      "name": "Coastal",
      "scoreA": 43,
      "scoreB": 27
    },
    {
      "name": "Cyclone",
      "scoreA": 11,
      "scoreB": 20
    }
  ],
  "verdict": "Leura has a lower overall climate risk score (36/100) compared to Leumeah (38/100). We recommend getting an address-level report for properties in both suburbs before making a purchase decision.",
  "verdictClass": "negative",
  "faq": [
    {
      "question": "Is Leumeah or Leura safer from flooding?",
      "answer": "Leumeah has a flood risk score of 27/100, while Leura scores 27/100. A lower score indicates lower flood risk. Get an address-level flood risk report for a specific property."
    },
    {
      "question": "Which suburb has lower bushfire risk?",
      "answer": "Leumeah scores 37/100 for bushfire risk. Leura scores 49/100. Fire risk depends on proximity to vegetation and local fire history."
    },
    {
      "question": "Should I buy in Leumeah or Leura?",
      "answer": "Both suburbs have climate considerations. Leura has a lower overall climate risk score. We recommend getting a full ClimateNest report for any specific property you're considering, which includes 8 hazard scores, insurance projections, and actionable recommendations."
    }
  ],
  "internalLinks": [
    {
      "label": "Leumeah Flood Risk",
      "url": "/suburbs/nsw/leumeah/flood-risk"
    },
    {
      "label": "Leura Flood Risk",
      "url": "/suburbs/nsw/leura/flood-risk"
    },
    {
      "label": "Leumeah Should I Buy?",
      "url": "/suburbs/nsw/leumeah/should-i-buy"
    },
    {
      "label": "Leura Should I Buy?",
      "url": "/suburbs/nsw/leura/should-i-buy"
    }
  ]
}