{
  "pageType": "comparison",
  "slug": "nickol-vs-nilgen",
  "seoTitle": "Nickol vs Nilgen — Climate Risk Comparison | ClimateNest",
  "seoDescription": "Compare climate risk scores between Nickol and Nilgen. See which suburb is safer from flood, bushfire, heat, and storm hazards.",
  "ogTitle": "Nickol vs Nilgen: Climate Safety",
  "ogDescription": "Data-driven comparison of climate risk in Nickol and Nilgen.",
  "heading": "Nickol vs Nilgen — Which is Safer?",
  "intro": "Compare climate risk between Nickol, Western Australia and Nilgen, Western Australia. Our analysis uses data from BOM, CSIRO, and state hazard authorities to score each suburb across 6 climate hazards.",
  "suburbs": [
    "nickol",
    "nilgen"
  ],
  "hazards": [
    {
      "name": "Flood",
      "scoreA": 22,
      "scoreB": 47
    },
    {
      "name": "Bushfire",
      "scoreA": 64,
      "scoreB": 33
    },
    {
      "name": "Heat",
      "scoreA": 31,
      "scoreB": 53
    },
    {
      "name": "Storm",
      "scoreA": 40,
      "scoreB": 25
    },
    {
      "name": "Coastal",
      "scoreA": 23,
      "scoreB": 11
    },
    {
      "name": "Cyclone",
      "scoreA": 15,
      "scoreB": 16
    }
  ],
  "verdict": "Nilgen has a lower overall climate risk score (31/100) compared to Nickol (33/100). We recommend getting an address-level report for properties in both suburbs before making a purchase decision.",
  "verdictClass": "negative",
  "faq": [
    {
      "question": "Is Nickol or Nilgen safer from flooding?",
      "answer": "Nickol has a flood risk score of 22/100, while Nilgen scores 47/100. A lower score indicates lower flood risk. Get an address-level flood risk report for a specific property."
    },
    {
      "question": "Which suburb has lower bushfire risk?",
      "answer": "Nickol scores 64/100 for bushfire risk. Nilgen scores 33/100. Fire risk depends on proximity to vegetation and local fire history."
    },
    {
      "question": "Should I buy in Nickol or Nilgen?",
      "answer": "Both suburbs have climate considerations. Nilgen has a lower overall climate risk score. We recommend getting a full ClimateNest report for any specific property you're considering, which includes 8 hazard scores, insurance projections, and actionable recommendations."
    }
  ],
  "internalLinks": [
    {
      "label": "Nickol Flood Risk",
      "url": "/suburbs/wa/nickol/flood-risk"
    },
    {
      "label": "Nilgen Flood Risk",
      "url": "/suburbs/wa/nilgen/flood-risk"
    },
    {
      "label": "Nickol Should I Buy?",
      "url": "/suburbs/wa/nickol/should-i-buy"
    },
    {
      "label": "Nilgen Should I Buy?",
      "url": "/suburbs/wa/nilgen/should-i-buy"
    }
  ]
}