{
  "pageType": "comparison",
  "slug": "tonimbuk-vs-tooan",
  "seoTitle": "Tonimbuk vs Tooan — Climate Risk Comparison | ClimateNest",
  "seoDescription": "Compare climate risk scores between Tonimbuk and Tooan. See which suburb is safer from flood, bushfire, heat, and storm hazards.",
  "ogTitle": "Tonimbuk vs Tooan: Climate Safety",
  "ogDescription": "Data-driven comparison of climate risk in Tonimbuk and Tooan.",
  "heading": "Tonimbuk vs Tooan — Which is Safer?",
  "intro": "Compare climate risk between Tonimbuk, Victoria and Tooan, Victoria. Our analysis uses data from BOM, CSIRO, and state hazard authorities to score each suburb across 6 climate hazards.",
  "suburbs": [
    "tonimbuk",
    "tooan"
  ],
  "hazards": [
    {
      "name": "Flood",
      "scoreA": 36,
      "scoreB": 46
    },
    {
      "name": "Bushfire",
      "scoreA": 40,
      "scoreB": 59
    },
    {
      "name": "Heat",
      "scoreA": 59,
      "scoreB": 76
    },
    {
      "name": "Storm",
      "scoreA": 42,
      "scoreB": 45
    },
    {
      "name": "Coastal",
      "scoreA": 18,
      "scoreB": 29
    },
    {
      "name": "Cyclone",
      "scoreA": 11,
      "scoreB": 28
    }
  ],
  "verdict": "Tonimbuk has a lower overall climate risk score (34/100) compared to Tooan (47/100). We recommend getting an address-level report for properties in both suburbs before making a purchase decision.",
  "verdictClass": "positive",
  "faq": [
    {
      "question": "Is Tonimbuk or Tooan safer from flooding?",
      "answer": "Tonimbuk has a flood risk score of 36/100, while Tooan scores 46/100. A lower score indicates lower flood risk. Get an address-level flood risk report for a specific property."
    },
    {
      "question": "Which suburb has lower bushfire risk?",
      "answer": "Tonimbuk scores 40/100 for bushfire risk. Tooan scores 59/100. Fire risk depends on proximity to vegetation and local fire history."
    },
    {
      "question": "Should I buy in Tonimbuk or Tooan?",
      "answer": "Both suburbs have climate considerations. Tonimbuk has a lower overall climate risk score. We recommend getting a full ClimateNest report for any specific property you're considering, which includes 8 hazard scores, insurance projections, and actionable recommendations."
    }
  ],
  "internalLinks": [
    {
      "label": "Tonimbuk Flood Risk",
      "url": "/suburbs/vic/tonimbuk/flood-risk"
    },
    {
      "label": "Tooan Flood Risk",
      "url": "/suburbs/vic/tooan/flood-risk"
    },
    {
      "label": "Tonimbuk Should I Buy?",
      "url": "/suburbs/vic/tonimbuk/should-i-buy"
    },
    {
      "label": "Tooan Should I Buy?",
      "url": "/suburbs/vic/tooan/should-i-buy"
    }
  ],
  "insurance": {
    "current": 4407,
    "projected2030": 6170,
    "projected2050": 11459
  },
  "valueImpact": {
    "dragPercent": 2.57,
    "description": "Properties in this area may face a 2.57% climate value drag over time due to rising insurance costs and climate adaptation expenses."
  },
  "riskLabel": "Moderate"
}